jumpstarter_driver_opendal/__init__.py
jumpstarter_driver_opendal/adapter.py
jumpstarter_driver_opendal/client.py
jumpstarter_driver_opendal/common.py
jumpstarter_driver_opendal/conftest.py
jumpstarter_driver_opendal/driver.py
jumpstarter_driver_opendal/driver_test.py
jumpstarter_driver_opendal/py.typed
jumpstarter_driver_opendal-0.7.4.dist-info/METADATA
jumpstarter_driver_opendal-0.7.4.dist-info/WHEEL
jumpstarter_driver_opendal-0.7.4.dist-info/entry_points.txt
jumpstarter_driver_opendal-0.7.4.dist-info/RECORD
